README.md
setup.py
platformTool.egg-info/PKG-INFO
platformTool.egg-info/SOURCES.txt
platformTool.egg-info/dependency_links.txt
platformTool.egg-info/requires.txt
platformTool.egg-info/top_level.txt
platform_tool/__init__.py
platform_tool/utils/__init__.py
platform_tool/utils/httpx_requests_utils.py
platform_tool/utils/id_card_utils.py
platform_tool/utils/log_utils.py
platform_tool/utils/yaml_utils.py